markdown_heading_numbering/__init__.py
markdown_heading_numbering/formatter.py
markdown_heading_numbering/main.py
markdown_heading_numbering-0.1.0.dist-info/licenses/LICENSE
markdown_heading_numbering-0.1.0.dist-info/METADATA
markdown_heading_numbering-0.1.0.dist-info/WHEEL
markdown_heading_numbering-0.1.0.dist-info/entry_points.txt
markdown_heading_numbering-0.1.0.dist-info/top_level.txt
markdown_heading_numbering-0.1.0.dist-info/RECORD
