Metadata-Version: 2.4
Name: markdown-heading-numbering
Version: 0.1.0
Summary: CLI and pre-commit hook to add hierarchical numbering to Markdown headings.
Author: jsh9
Requires-Python: >=3.10
License-File: LICENSE
Requires-Dist: click>=8.0
Provides-Extra: dev
Requires-Dist: pytest>=7.0; extra == "dev"
Dynamic: license-file
